rtl/core/regfile.sv
/*
* REGISTER FILE (RV64I + Scoreboard + NPU Dual-Read + Forwarding Hooks)
*
* Designed for OSYRYS-64 core with integrated NPU
*
* - 64-bit, 32 general-purpose registers
* - Dual write ports (A and B)
* - Scoreboard hazard tracking
* - External dual-read (for NPU/MMU/vector ops)
* - Forwarding-ready output ports
*/

`timescale 1ns/1ps

module regfile (
    input  logic         clk,
    input  logic         rst_n,

    // CPU Read Ports
    input  logic [4:0]   address1,
    input  logic [4:0]   address2,
    input logic [4:0]    address3,
    output logic [63:0]  read_data1,
    output logic [63:0]  read_data2,

    // Write Port A
    input  logic         write_enable_a,
    input  logic [4:0]   write_addr_a,
    input  logic [63:0]  write_data_a,

    // Write Port B (NPU / forwarding)
    input  logic         write_enable_b,
    input  logic [4:0]   write_addr_b,
    input  logic [63:0]  write_data_b,

    // Coprocessor Dual Read Ports (e.g., NPU)
    input  logic [4:0]   ext_address1,
    input  logic [4:0]   ext_address2,
    output logic [63:0]  ext_data1,
    output logic [63:0]  ext_data2,

    // Scoreboard output (hazard detection unit uses this)
    output logic [31:0]  reg_pending_writes
);

    // 32 x 64-bit general-purpose registers
    logic [63:0] registers [0:31];

    // Scoreboard: 1 if pending write
    logic [31:0] scoreboard;

    // -------------------------------
    // Reset and Write Operations
    // -------------------------------
    always_ff @(posedge clk) begin
        if (rst_n == 0) begin // or: if (rst_n == 1'b0) 
            for (int i = 0; i < 32; i++) begin
                registers[i] <= 64'd0;
                scoreboard[i] <= 1'b0;
            end
        end else begin
            // Write A
            if (write_enable_a && write_addr_a != 5'd0) begin
                registers[write_addr_a] <= write_data_a;
                scoreboard[write_addr_a] <= 1'b0; // Clear pending bit
                $display("[regfile] Write A: x%0d <= 0x%h", write_addr_a, write_data_a);
            end

            // Write B (used by NPU/co-proc/forwarding)
            if (write_enable_b && write_addr_b != 5'd0 && write_addr_b != write_addr_a) begin
                registers[write_addr_b] <= write_data_b;
                scoreboard[write_addr_b] <= 1'b0;
                $display("[regfile] Write B: x%0d <= 0x%h", write_addr_b, write_data_b);
            end

            // Set scoreboard bits when write is issued (could be triggered earlier)
            if (write_enable_a && write_addr_a != 5'd0)
                scoreboard[write_addr_a] <= 1'b1;
            if (write_enable_b && write_addr_b != 5'd0)
                scoreboard[write_addr_b] <= 1'b1;
        end
    end

    // -------------------------------
    // Synchronous Read Ports (CPU)
    // -------------------------------
    always_comb begin
        read_data1 = (address1 == 5'd0) ? 64'd0 : registers[address1];
        read_data2 = (address2 == 5'd0) ? 64'd0 : registers[address2];

        // External ports for NPU / vector / coprocessor
        ext_data1 = (ext_address1 == 5'd0) ? 64'd0 : registers[ext_address1];
        ext_data2 = (ext_address2 == 5'd0) ? 64'd0 : registers[ext_address2];
    end

    // -------------------------------
    // Output Scoreboard
    // -------------------------------
    assign reg_pending_writes = scoreboard;

endmodule

tb/regfile_tb/regfile_tb.sv
`timescale 1ns/1ps

module regfile_tb;

  // Clock and Reset
  logic clk = 0;
  logic rst_n = 0;

  // CPU read ports
  logic [4:0] address1, address2, address3;
  logic [63:0] read_data1, read_data2;

  // Write Ports A and B
  logic write_enable_a, write_enable_b;
  logic [4:0] write_addr_a, write_addr_b;
  logic [63:0] write_data_a, write_data_b;

  // External dual-read (NPU)
  logic [4:0] ext_address1, ext_address2;
  logic [63:0] ext_data1, ext_data2;

  // Scoreboard output
  logic [31:0] reg_pending_writes;

  // Instantiate DUT
  regfile uut (
    .clk(clk),
    .rst_n(rst_n),
    .address1(address1),
    .address2(address2),
    .address3(address3),
    .read_data1(read_data1),
    .read_data2(read_data2),
    .write_enable_a(write_enable_a),
    .write_addr_a(write_addr_a),
    .write_data_a(write_data_a),
    .write_enable_b(write_enable_b),
    .write_addr_b(write_addr_b),
    .write_data_b(write_data_b),
    .ext_address1(ext_address1),
    .ext_address2(ext_address2),
    .ext_data1(ext_data1),
    .ext_data2(ext_data2),
    .reg_pending_writes(reg_pending_writes)
  );

  // Clock Generation
  always #5 clk <= ~clk;

  initial begin
    $dumpfile("regfile_tb.vcd");
    $dumpvars(0, regfile_tb);

    // Initial values
    address1 = 0;
    address2 = 0;
    address3 = 0;
    write_enable_a = 0;
    write_enable_b = 0;
    write_addr_a = 0;
    write_data_a = 0;
    write_addr_b = 0;
    write_data_b = 0;
    ext_address1 = 0;
    ext_address2 = 0;

    // Reset
    #2 rst_n = 0;
    #10 rst_n = 1;

    // Write to reg x5 via Port A
    #10;
    write_enable_a = 1;
    write_addr_a = 5;
    write_data_a = 64'hdeadbeefdeadbeef;
    #10;
    write_enable_a = 0;

    // Write to reg x10 via Port B
    #10;
    write_enable_b = 1;
    write_addr_b = 10;
    write_data_b = 64'hcafef00dcafef00d;
    #10;
    write_enable_b = 0;

    // Read from x5 and x10 via CPU read ports
    #10;
    address1 = 5;
    address2 = 10;
    #10;

    $display("CPU Read x5 = 0x%h (Expected: 0xdeadbeefdeadbeef)", read_data1);
    $display("CPU Read x10 = 0x%h (Expected: 0xcafef00dcafef00d)", read_data2);

    // External NPU read from same
    ext_address1 = 5;
    ext_address2 = 10;
    #10;
    $display("EXT Read x5 = 0x%h", ext_data1);
    $display("EXT Read x10 = 0x%h", ext_data2);

    // Display scoreboard
    $display("Scoreboard: %b", reg_pending_writes);

    #20 $finish;
  end

endmodule

tb/regfile_tb/regfile_tb.vcd
$version Generated by VerilatedVcd $end
$timescale 1ps $end
 $scope module TOP $end
  $scope module regfile_tb $end
   $var wire 1 s clk $end
   $var wire 1 # rst_n $end
   $var wire 5 $ address1 [4:0] $end
   $var wire 5 % address2 [4:0] $end
   $var wire 5 & address3 [4:0] $end
   $var wire 64 t read_data1 [63:0] $end
   $var wire 64 v read_data2 [63:0] $end
   $var wire 1 ' write_enable_a $end
   $var wire 1 ( write_enable_b $end
   $var wire 5 ) write_addr_a [4:0] $end
   $var wire 5 * write_addr_b [4:0] $end
   $var wire 64 + write_data_a [63:0] $end
   $var wire 64 - write_data_b [63:0] $end
   $var wire 5 / ext_address1 [4:0] $end
   $var wire 5 0 ext_address2 [4:0] $end
   $var wire 64 x ext_data1 [63:0] $end
   $var wire 64 z ext_data2 [63:0] $end
   $var wire 32 1 reg_pending_writes [31:0] $end
   $scope module uut $end
    $var wire 1 s clk $end
    $var wire 1 # rst_n $end
    $var wire 5 $ address1 [4:0] $end
    $var wire 5 % address2 [4:0] $end
    $var wire 5 & address3 [4:0] $end
    $var wire 64 t read_data1 [63:0] $end
    $var wire 64 v read_data2 [63:0] $end
    $var wire 1 ' write_enable_a $end
    $var wire 5 ) write_addr_a [4:0] $end
    $var wire 64 + write_data_a [63:0] $end
    $var wire 1 ( write_enable_b $end
    $var wire 5 * write_addr_b [4:0] $end
    $var wire 64 - write_data_b [63:0] $end
    $var wire 5 / ext_address1 [4:0] $end
    $var wire 5 0 ext_address2 [4:0] $end
    $var wire 64 x ext_data1 [63:0] $end
    $var wire 64 z ext_data2 [63:0] $end
    $var wire 32 1 reg_pending_writes [31:0] $end
    $var wire 64 2 registers[0] [63:0] $end
    $var wire 64 4 registers[1] [63:0] $end
    $var wire 64 6 registers[2] [63:0] $end
    $var wire 64 8 registers[3] [63:0] $end
    $var wire 64 : registers[4] [63:0] $end
    $var wire 64 < registers[5] [63:0] $end
    $var wire 64 > registers[6] [63:0] $end
    $var wire 64 @ registers[7] [63:0] $end
    $var wire 64 B registers[8] [63:0] $end
    $var wire 64 D registers[9] [63:0] $end
    $var wire 64 F registers[10] [63:0] $end
    $var wire 64 H registers[11] [63:0] $end
    $var wire 64 J registers[12] [63:0] $end
    $var wire 64 L registers[13] [63:0] $end
    $var wire 64 N registers[14] [63:0] $end
    $var wire 64 P registers[15] [63:0] $end
    $var wire 64 R registers[16] [63:0] $end
    $var wire 64 T registers[17] [63:0] $end
    $var wire 64 V registers[18] [63:0] $end
    $var wire 64 X registers[19] [63:0] $end
    $var wire 64 Z registers[20] [63:0] $end
    $var wire 64 \ registers[21] [63:0] $end
    $var wire 64 ^ registers[22] [63:0] $end
    $var wire 64 ` registers[23] [63:0] $end
    $var wire 64 b registers[24] [63:0] $end
    $var wire 64 d registers[25] [63:0] $end
    $var wire 64 f registers[26] [63:0] $end
    $var wire 64 h registers[27] [63:0] $end
    $var wire 64 j registers[28] [63:0] $end
    $var wire 64 l registers[29] [63:0] $end
    $var wire 64 n registers[30] [63:0] $end
    $var wire 64 p registers[31] [63:0] $end
    $var wire 32 1 scoreboard [31:0] $end
    $scope module unnamedblk1 $end
     $var wire 32 r i [31:0] $end
    $upscope $end
   $upscope $end
  $upscope $end
 $upscope $end
$enddefinitions $end


#0
0#
b00000 $
b00000 %
b00000 &
0'
0(
b00000 )
b00000 *
b0000000000000000000000000000000000000000000000000000000000000000 +
b0000000000000000000000000000000000000000000000000000000000000000 -
b00000 /
b00000 0
b00000000000000000000000000000000 1
b0000000000000000000000000000000000000000000000000000000000000000 2
b0000000000000000000000000000000000000000000000000000000000000000 4
b0000000000000000000000000000000000000000000000000000000000000000 6
b0000000000000000000000000000000000000000000000000000000000000000 8
b0000000000000000000000000000000000000000000000000000000000000000 :
b0000000000000000000000000000000000000000000000000000000000000000 <
b0000000000000000000000000000000000000000000000000000000000000000 >
b0000000000000000000000000000000000000000000000000000000000000000 @
b0000000000000000000000000000000000000000000000000000000000000000 B
b0000000000000000000000000000000000000000000000000000000000000000 D
b0000000000000000000000000000000000000000000000000000000000000000 F
b0000000000000000000000000000000000000000000000000000000000000000 H
b0000000000000000000000000000000000000000000000000000000000000000 J
b0000000000000000000000000000000000000000000000000000000000000000 L
b0000000000000000000000000000000000000000000000000000000000000000 N
b0000000000000000000000000000000000000000000000000000000000000000 P
b0000000000000000000000000000000000000000000000000000000000000000 R
b0000000000000000000000000000000000000000000000000000000000000000 T
b0000000000000000000000000000000000000000000000000000000000000000 V
b0000000000000000000000000000000000000000000000000000000000000000 X
b0000000000000000000000000000000000000000000000000000000000000000 Z
b0000000000000000000000000000000000000000000000000000000000000000 \
b0000000000000000000000000000000000000000000000000000000000000000 ^
b0000000000000000000000000000000000000000000000000000000000000000 `
b0000000000000000000000000000000000000000000000000000000000000000 b
b0000000000000000000000000000000000000000000000000000000000000000 d
b0000000000000000000000000000000000000000000000000000000000000000 f
b0000000000000000000000000000000000000000000000000000000000000000 h
b0000000000000000000000000000000000000000000000000000000000000000 j
b0000000000000000000000000000000000000000000000000000000000000000 l
b0000000000000000000000000000000000000000000000000000000000000000 n
b0000000000000000000000000000000000000000000000000000000000000000 p
b00000000000000000000000000000000 r
0s
b0000000000000000000000000000000000000000000000000000000000000000 t
b0000000000000000000000000000000000000000000000000000000000000000 v
b0000000000000000000000000000000000000000000000000000000000000000 x
b0000000000000000000000000000000000000000000000000000000000000000 z
#2000
#5000
b00000000000000000000000000100000 r
1s
#10000
0s
#12000
1#
#15000
1s
#20000
0s
#22000
1'
b00101 )
b1101111010101101101111101110111111011110101011011011111011101111 +
#25000
b00000000000000000000000000100000 1
b1101111010101101101111101110111111011110101011011011111011101111 <
1s
#30000
0s
#32000
0'
#35000
1s
#40000
0s
#42000
1(
b01010 *
b1100101011111110111100000000110111001010111111101111000000001101 -
#45000
b00000000000000000000010000100000 1
b1100101011111110111100000000110111001010111111101111000000001101 F
1s
#50000
0s
#52000
0(
#55000
1s
#60000
0s
#62000
b00101 $
b01010 %
b1101111010101101101111101110111111011110101011011011111011101111 t
b1100101011111110111100000000110111001010111111101111000000001101 v
#65000
1s
#70000
0s
#72000
b00101 /
b01010 0
b1101111010101101101111101110111111011110101011011011111011101111 x
b1100101011111110111100000000110111001010111111101111000000001101 z
